pygorithm/__init__.py
pygorithm/binary/__init__.py
pygorithm/binary/ascii.py
pygorithm/binary/base10.py
pygorithm/binary/base16.py
pygorithm/binary/base2.py
pygorithm/binary/binary_utils.py
pygorithm/data_structures/__init__.py
pygorithm/data_structures/graph.py
pygorithm/data_structures/heap.py
pygorithm/data_structures/linked_list.py
pygorithm/data_structures/quadtree.py
pygorithm/data_structures/queue.py
pygorithm/data_structures/stack.py
pygorithm/data_structures/tree.py
pygorithm/data_structures/trie.py
pygorithm/dynamic_programming/__init__.py
pygorithm/dynamic_programming/binary_knapsack.py
pygorithm/dynamic_programming/lis.py
pygorithm/fibonacci/__init__.py
pygorithm/fibonacci/generator.py
pygorithm/fibonacci/goldenratio.py
pygorithm/fibonacci/memoization.py
pygorithm/fibonacci/recursion.py
pygorithm/geometry/__init__.py
pygorithm/geometry/axisall.py
pygorithm/geometry/line2.py
pygorithm/geometry/polygon2.py
pygorithm/geometry/rect2.py
pygorithm/geometry/rect_broad_phase.py
pygorithm/geometry/vector2.py
pygorithm/greedy_algorithm/__init__.py
pygorithm/greedy_algorithm/activity_selection.py
pygorithm/greedy_algorithm/fractional_knapsack.py
pygorithm/math/__init__.py
pygorithm/math/conversion.py
pygorithm/math/factorial.py
pygorithm/math/lcm.py
pygorithm/math/lcm_using_gcd.py
pygorithm/math/matrix_operations.py
pygorithm/math/pascals_triangle.py
pygorithm/math/sieve_of_eratosthenes.py
pygorithm/pathfinding/__init__.py
pygorithm/pathfinding/astar.py
pygorithm/pathfinding/dijkstra.py
pygorithm/searching/__init__.py
pygorithm/searching/binary_search.py
pygorithm/searching/breadth_first_search.py
pygorithm/searching/depth_first_search.py
pygorithm/searching/exponential_search.py
pygorithm/searching/interpolation_search.py
pygorithm/searching/linear_search.py
pygorithm/searching/quick_select.py
pygorithm/searching/ternary_search.py
pygorithm/sorting/__init__.py
pygorithm/sorting/bubble_sort.py
pygorithm-1.0.4.dist-info/DESCRIPTION.rst
pygorithm-1.0.4.dist-info/METADATA
pygorithm-1.0.4.dist-info/RECORD
pygorithm-1.0.4.dist-info/WHEEL
pygorithm-1.0.4.dist-info/metadata.json
pygorithm-1.0.4.dist-info/top_level.txt
