Metadata-Version: 2.0
Name: pygorithm
Version: 1.0.4
Summary: A Python algorithms module for learning
Home-page: https://github.com/OmkarPathak/pygorithm
Author: Omkar Pathak
Author-email: omkarpathak27@gmail.com
License: MIT
Platform: UNKNOWN
Classifier: Intended Audience :: Developers
Classifier: Topic :: Software Development :: Libraries
Classifier: License :: OSI Approved :: MIT License
Classifier: Programming Language :: Python :: 2.7
Classifier: Programming Language :: Python :: 3
Classifier: Programming Language :: Python :: 3.3
Classifier: Programming Language :: Python :: 3.4
Classifier: Programming Language :: Python :: 3.5
Classifier: Programming Language :: Python :: 3.6
